{
  "chargers": [
    {
      "id": 1,
      "name": "Ann Arbor City Hall",
      "chargePoint": "62 - 62.5 kW Residential",
      "price": 0.52,
      "time": "Open 24/7",
      "parking": "Parking: Free",
      "type": "Level 1",
      "address": {
        "street": "R. Mathias Velho",
        "city": "Canoas",
        "number": 235,
        "country": "Brazil"
      },
      "location": {
        "latitude": -29.9109446,
        "longitude": -51.18435968
      },
      "available": 1
    },
    {
      "id": 2,
      "name": "Meijer",
      "chargePoint": "31 - 62.5 kW Shopping Center",
      "price": 0.86,
      "time": "Open 24/7",
      "parking": "Parking: Free",
      "type": "Level 2",
      "address": {
        "street": "R. Mathias Velho",
        "city": "Canoas",
        "number": 235,
        "country": "Brazil"
      },
      "location": {
        "latitude": -29.91098302,
        "longitude": -51.18517898
      },
      "available": 1
    },
    {
      "id": 3,
      "name": "Ibis Canoas Shopping",
      "chargePoint": "AutochargeShopping Center",
      "price": 0.52,
      "time": "Open 24/7",
      "parking": "Parking: Free",
      "type": "Level 2",
      "address": {
        "street": "R. Mathias Velho",
        "city": "Canoas",
        "number": 235,
        "country": "Brazil"
      },
      "location": {
        "latitude": -29.91139809,
        "longitude": -51.18418962
      },
      "available": 0
    },
    {
      "id": 4,
      "name": "Cubo Self Storage",
      "chargePoint": "AutochargeShopping Center",
      "price": 0.52,
      "time": "Open 24/7",
      "parking": "Parking: Free",
      "type": "Level 2",
      "address": {
        "street": "R. Mathias Velho",
        "city": "Canoas",
        "number": 200,
        "country": "Brazil"
      },
      "location": {
        "latitude": -29.91043983,
        "longitude": -51.18290348
      },
      "available": 0
    },
    {
      "id": 5,
      "name": "Cubo Self Storage",
      "chargePoint": "AutochargeShopping Center",
      "price": 0.52,
      "time": "Open 24/7",
      "parking": "Parking: Free",
      "type": "Level 2",
      "address": {
        "street": "R. Mathias Velho",
        "city": "Canoas",
        "number": 200,
        "country": "Brazil"
      },
      "location": {
        "latitude": -29.90899459,
        "longitude": -51.18478278
      },
      "available": 1
    },
    {
      "id": 6,
      "name": "Cubo Self Storage",
      "chargePoint": "AutochargeShopping Center",
      "price": 0.52,
      "time": "Open 24/7",
      "parking": "Parking: Free",
      "type": "Level 2",
      "address": {
        "street": "R. Mathias Velho",
        "city": "Canoas",
        "number": 200,
        "country": "Brazil"
      },
      "location": {
        "latitude": -29.90887369,
        "longitude": -51.18350069
      },
      "available": 0
    },
    {
      "id": 7,
      "name": "Canoas Shopping",
      "chargePoint": "AutochargeShopping Center",
      "price": 0.52,
      "time": "Open 24/7",
      "parking": "Parking: Free",
      "type": "Level 2",
      "address": {
        "street": "R. Mathias Velho",
        "city": "Canoas",
        "number": 200,
        "country": "Brazil"
      },
      "location": {
        "latitude": -29.90873517,
        "longitude": -51.182393
      },
      "available": 1
    },
    {
      "id": 8,
      "name": "Carrefour",
      "chargePoint": "Carrefour Center",
      "price": 0.52,
      "time": "Open 24/7",
      "parking": "Parking: Free",
      "type": "Level 2",
      "address": {
        "street": "R. Mathias Velho",
        "city": "Canoas",
        "number": 200,
        "country": "Brazil"
      },
      "location": {
        "latitude": -29.91010529,
        "longitude": -51.18608862
      },
      "available": 0
    },
    {
      "id": 9,
      "name": "Carrefour",
      "chargePoint": "Carrefour Center",
      "price": 0.52,
      "time": "Open 24/7",
      "parking": "Parking: Free",
      "type": "Level 2",
      "address": {
        "street": "R. Mathias Velho",
        "city": "Canoas",
        "number": 200,
        "country": "Brazil"
      },
      "location": {
        "latitude": -29.90866858,
        "longitude": -51.18663847
      },
      "available": 1
    },
    {
      "id": 1,
      "name": "Ann Arbor City Hall",
      "chargePoint": "",
      "price": 0,
      "time": "O",
      "parking": "Parking: Free",
      "type": "Level 1",
      "address": {
        "street": "-29.911457401157797 / -51.183187076227746",
        "city": "",
        "number": 0,
        "country": ""
      },
      "location": {
        "latitude": -29.911457401157797,
        "longitude": -51.183187076227746
      },
      "available": 0
    },
    {
      "id": 1,
      "name": "Ann Arbor City Hall",
      "chargePoint": "",
      "price": 0,
      "time": "O",
      "parking": "Parking: Free",
      "type": "Level 1",
      "address": {
        "street": "-29.911543786746996 / -51.18217138502862",
        "city": "",
        "number": 0,
        "country": ""
      },
      "location": {
        "latitude": -29.911543786746996,
        "longitude": -51.18217138502862
      },
      "available": 0
    },
    {
      "id": 1,
      "name": "Ann Arbor City Hall",
      "chargePoint": "",
      "price": 0,
      "time": "O",
      "parking": "Parking: Free",
      "type": "Level 1",
      "address": {
        "street": "-29.909262814420345 / -51.18104543083011",
        "city": "",
        "number": 0,
        "country": ""
      },
      "location": {
        "latitude": -29.909262814420345,
        "longitude": -51.18104543083011
      },
      "available": 0
    },
    {
      "id": 1,
      "name": "Ann Arbor City Hall",
      "chargePoint": "",
      "price": 0,
      "time": "O",
      "parking": "Parking: Free",
      "type": "Level 1",
      "address": {
        "street": "-29.907632107905837 / -51.18727988097149",
        "city": "",
        "number": 0,
        "country": ""
      },
      "location": {
        "latitude": -29.907632107905837,
        "longitude": -51.18727988097149
      },
      "available": 0
    },
    {
      "id": 1,
      "name": "Ann Arbor City Hall",
      "chargePoint": "",
      "price": 0,
      "time": "O",
      "parking": "Parking: Free",
      "type": "Level 1",
      "address": {
        "street": "-29.911894842192094 / -51.18560013801524",
        "city": "",
        "number": 0,
        "country": ""
      },
      "location": {
        "latitude": -29.911894842192094,
        "longitude": -51.18560013801524
      },
      "available": 0
    }
  ],
  "add-charger": [
    {
      "id": 1,
      "name": "Ann Arbor City Hall",
      "chargePoint": "62 - 62.5 kW Residential",
      "price": 0.52,
      "time": "Open 24/7",
      "parking": "Parking: Free",
      "type": "Level 1",
      "address": {
        "street": "R. Mathias Velho",
        "city": "Canoas",
        "number": 235,
        "country": "Brazil"
      },
      "location": {
        "latitude": -29.9109446,
        "longitude": -51.18435968
      },
      "available": 1
    },
    {
      "id": 2,
      "name": "Meijer",
      "chargePoint": "31 - 62.5 kW Shopping Center",
      "price": 0.86,
      "time": "Open 24/7",
      "parking": "Parking: Free",
      "type": "Level 2",
      "address": {
        "street": "R. Mathias Velho",
        "city": "Canoas",
        "number": 235,
        "country": "Brazil"
      },
      "location": {
        "latitude": -29.91098302,
        "longitude": -51.18517898
      },
      "available": 1
    },
    {
      "id": 3,
      "name": "Ibis Canoas Shopping",
      "chargePoint": "AutochargeShopping Center",
      "price": 0.52,
      "time": "Open 24/7",
      "parking": "Parking: Free",
      "type": "Level 2",
      "address": {
        "street": "R. Mathias Velho",
        "city": "Canoas",
        "number": 235,
        "country": "Brazil"
      },
      "location": {
        "latitude": -29.91139809,
        "longitude": -51.18418962
      },
      "available": 0
    },
    {
      "id": 4,
      "name": "Cubo Self Storage",
      "chargePoint": "AutochargeShopping Center",
      "price": 0.52,
      "time": "Open 24/7",
      "parking": "Parking: Free",
      "type": "Level 2",
      "address": {
        "street": "R. Mathias Velho",
        "city": "Canoas",
        "number": 200,
        "country": "Brazil"
      },
      "location": {
        "latitude": -29.91043983,
        "longitude": -51.18290348
      },
      "available": 0
    },
    {
      "id": 5,
      "name": "Cubo Self Storage",
      "chargePoint": "AutochargeShopping Center",
      "price": 0.52,
      "time": "Open 24/7",
      "parking": "Parking: Free",
      "type": "Level 2",
      "address": {
        "street": "R. Mathias Velho",
        "city": "Canoas",
        "number": 200,
        "country": "Brazil"
      },
      "location": {
        "latitude": -29.90899459,
        "longitude": -51.18478278
      },
      "available": 1
    },
    {
      "id": 6,
      "name": "Cubo Self Storage",
      "chargePoint": "AutochargeShopping Center",
      "price": 0.52,
      "time": "Open 24/7",
      "parking": "Parking: Free",
      "type": "Level 2",
      "address": {
        "street": "R. Mathias Velho",
        "city": "Canoas",
        "number": 200,
        "country": "Brazil"
      },
      "location": {
        "latitude": -29.90887369,
        "longitude": -51.18350069
      },
      "available": 0
    },
    {
      "id": 7,
      "name": "Canoas Shopping",
      "chargePoint": "AutochargeShopping Center",
      "price": 0.52,
      "time": "Open 24/7",
      "parking": "Parking: Free",
      "type": "Level 2",
      "address": {
        "street": "R. Mathias Velho",
        "city": "Canoas",
        "number": 200,
        "country": "Brazil"
      },
      "location": {
        "latitude": -29.90873517,
        "longitude": -51.182393
      },
      "available": 1
    },
    {
      "id": 8,
      "name": "Carrefour",
      "chargePoint": "Carrefour Center",
      "price": 0.52,
      "time": "Open 24/7",
      "parking": "Parking: Free",
      "type": "Level 2",
      "address": {
        "street": "R. Mathias Velho",
        "city": "Canoas",
        "number": 200,
        "country": "Brazil"
      },
      "location": {
        "latitude": -29.91010529,
        "longitude": -51.18608862
      },
      "available": 0
    },
    {
      "id": 9,
      "name": "Carrefour",
      "chargePoint": "Carrefour Center",
      "price": 0.52,
      "time": "Open 24/7",
      "parking": "Parking: Free",
      "type": "Level 2",
      "address": {
        "street": "R. Mathias Velho",
        "city": "Canoas",
        "number": 200,
        "country": "Brazil"
      },
      "location": {
        "latitude": -29.90866858,
        "longitude": -51.18663847
      },
      "available": 1
    },
    {
      "id": "422c",
      "latitude": -29.911992924811106,
      "longitude": -51.18560639111958
    },
    {
      "id": "3b98",
      "latitude": -29.91277406416783,
      "longitude": -51.18574421972319
    },
    {
      "id": "2115",
      "latitude": -29.915720193466253,
      "longitude": -51.186160598213384
    },
    {
      "id": "5441",
      "latitude": -29.91098302,
      "longitude": -51.18517898
    },
    {
      "id": "ceb3",
      "latitude": -29.91098302,
      "longitude": -51.18517898
    },
    {
      "id": "fc6a",
      "latitude": -29.9109446,
      "longitude": -51.18435968
    },
    {
      "id": "4b58",
      "latitude": -29.91139809,
      "longitude": -51.18418962
    },
    {
      "id": "e99c",
      "latitude": -29.914351701348274,
      "longitude": -51.182554759949056
    },
    {
      "id": "b3c2",
      "latitude": -29.911637028990942,
      "longitude": -51.18196739790707
    },
    {
      "id": "c2dc",
      "latitude": -29.905600835988395,
      "longitude": -51.179675105763096
    }
  ]
}